confluence_assistant_skills_lib/__init__.py
confluence_assistant_skills_lib/adf_helper.py
confluence_assistant_skills_lib/autocomplete_cache.py
confluence_assistant_skills_lib/config_manager.py
confluence_assistant_skills_lib/confluence_client.py
confluence_assistant_skills_lib/credential_manager.py
confluence_assistant_skills_lib/error_handler.py
confluence_assistant_skills_lib/formatters.py
confluence_assistant_skills_lib/markdown_parser.py
confluence_assistant_skills_lib/space_context.py
confluence_assistant_skills_lib/validators.py
confluence_assistant_skills_lib/xhtml_helper.py
confluence_assistant_skills_lib/cli/__init__.py
confluence_assistant_skills_lib/cli/cli_utils.py
confluence_assistant_skills_lib/cli/helpers.py
confluence_assistant_skills_lib/cli/main.py
confluence_assistant_skills_lib/cli/commands/__init__.py
confluence_assistant_skills_lib/cli/commands/admin_cmds.py
confluence_assistant_skills_lib/cli/commands/analytics_cmds.py
confluence_assistant_skills_lib/cli/commands/attachment_cmds.py
confluence_assistant_skills_lib/cli/commands/bulk_cmds.py
confluence_assistant_skills_lib/cli/commands/comment_cmds.py
confluence_assistant_skills_lib/cli/commands/hierarchy_cmds.py
confluence_assistant_skills_lib/cli/commands/jira_cmds.py
confluence_assistant_skills_lib/cli/commands/label_cmds.py
confluence_assistant_skills_lib/cli/commands/ops_cmds.py
confluence_assistant_skills_lib/cli/commands/page_cmds.py
confluence_assistant_skills_lib/cli/commands/permission_cmds.py
confluence_assistant_skills_lib/cli/commands/property_cmds.py
confluence_assistant_skills_lib/cli/commands/search_cmds.py
confluence_assistant_skills_lib/cli/commands/space_cmds.py
confluence_assistant_skills_lib/cli/commands/template_cmds.py
confluence_assistant_skills_lib/cli/commands/watch_cmds.py
confluence_assistant_skills_lib/mock/__init__.py
confluence_assistant_skills_lib/mock/base.py
confluence_assistant_skills_lib/mock/client.py
confluence_assistant_skills_lib/mock/mixins/__init__.py
confluence_assistant_skills_lib-0.4.1.dist-info/METADATA
confluence_assistant_skills_lib-0.4.1.dist-info/WHEEL
confluence_assistant_skills_lib-0.4.1.dist-info/entry_points.txt
confluence_assistant_skills_lib-0.4.1.dist-info/licenses/LICENSE
confluence_assistant_skills_lib-0.4.1.dist-info/RECORD
